Metadata-Version: 2.1
Name: hack4u2i3
Version: 0.5.0
Summary: Una bibilioteca para consultar cursos de hack4u.
Home-page: https://hack4u.io
Author: Samuel
